Metadata-Version: 2.1
Name: seq-conv
Version: 1.0.2
Summary: Graph convolutional operator that uses a LSTM as a filter
Home-page: https://github.com/shobrook/SeqConv
Author: shobrook
Author-email: shobrookj@gmail.com
License: MIT
Keywords: gnn,graph-neural-network,convolution,pytorch,graph,lstm,rnn,sequence
Platform: UNKNOWN
Requires-Python: >=3
